devious/__init__.py
devious/__main__.py
devious/build.py
devious/cli.py
devious/config.py
devious/create.py
devious/debug.py
devious/deploy.py
devious/inspect.py
devious/install.py
devious/py.typed
devious/registration.py
devious/run.py
devious/stop.py
devious/test.py
devious/update.py
devious/utils.py
devious/verify.py
devious/targets/__init__.py
devious/targets/target.py
devious/targets/django_app/__init__.py
devious/targets/django_app/django_app.py
devious/targets/django_app/config/Dockerfile
devious/targets/django_app/config/daemon.json
devious/targets/django_app/config/debug_settings.py
devious/targets/django_app/config/dhparam.pem
devious/targets/django_app/config/nginx.default
devious/targets/django_app/config/nginx.default.unsafe
devious/targets/django_app/config/settings.py
devious/targets/django_app/config/start-server.sh
devious/targets/iac/__init__.py
devious/targets/iac/iac.py
devious/targets/iac/iac_config/Dockerfile
devious/targets/iac/iac_config/ansible.yaml
devious/targets/iac/iac_config/ansible_requirements.yaml
devious/targets/iac/iac_config/cloud-init.yaml
devious/targets/iac/iac_config/daemon.json
devious/targets/iac/iac_config/main.tf
devious/targets/iac/iac_config/start-server.sh
devious/targets/iac/iac_config/workflow.yaml
devious/targets/iac/nginx_config/api_backends.conf
devious/targets/iac/nginx_config/api_gateway.conf
devious/targets/iac/nginx_config/api_json_errors.conf
devious/targets/iac/nginx_config/nginx.conf
devious/targets/microservice/__init__.py
devious/targets/microservice/microservice.py
devious/targets/microservice/microservice_config/Dockerfile
devious/targets/microservice/microservice_config/api.conf
devious/targets/microservice/microservice_config/api_backend.conf
devious/targets/microservice/microservice_config/daemon.json
devious/targets/microservice/microservice_config/start-server.sh
devious/targets/microservice/nginx_config/api_backends.conf
devious/targets/microservice/nginx_config/api_gateway.conf
devious-0.19.0.dist-info/METADATA
devious-0.19.0.dist-info/WHEEL
devious-0.19.0.dist-info/entry_points.txt
devious-0.19.0.dist-info/RECORD
